vulnerabilities/__init__.py
vulnerabilities/sarif.py
vulnerabilities/tools/bandit/__init__.py
vulnerabilities/tools/bandit/parser.py
vulnerabilities/tools/cyclonedx/__init__.py
vulnerabilities/tools/cyclonedx/parser.py
vulnerabilities/tools/semgrep/__init__.py
vulnerabilities/tools/semgrep/parser.py
vulnerabilities/tools/snyk/__init__.py
vulnerabilities/tools/snyk/parser.py
vulnerabilities-0.0.5.dist-info/LICENSE
vulnerabilities-0.0.5.dist-info/WHEEL
vulnerabilities-0.0.5.dist-info/METADATA
vulnerabilities-0.0.5.dist-info/RECORD
