Metadata-Version: 2.1
Name: vulnerabilities
Version: 0.0.5
Summary: Module to manage vulnerabilities
Home-page: https://github.com/damiencarol/vulnerabilities
License: BSD-3-Clause
Author: Damien Carol
Author-email: damien.carol@gmail.com
Requires-Dist: python-dateutil
Requires-Dist: cvss
Requires-Dist: defusedxml
